mseep_pymcpautogui-0.1.3.dist-info/licenses/LICENSE
pymcpautogui/__init__.py
pymcpautogui/server.py
mseep_pymcpautogui-0.1.3.dist-info/METADATA
mseep_pymcpautogui-0.1.3.dist-info/WHEEL
mseep_pymcpautogui-0.1.3.dist-info/top_level.txt
mseep_pymcpautogui-0.1.3.dist-info/RECORD
