Metadata-Version: 2.4
Name: mseep-pymcpautogui
Version: 0.1.3
Summary: Add your description here
Home-page: 
Author: mseep
Author-email: mseep <support@skydeck.ai>
Maintainer-email: mseep <support@skydeck.ai>
Requires-Python: >=3.6
License-File: LICENSE
Requires-Dist: mcp[cli]>=1.6.0
Requires-Dist: pyautogui>=0.9.54
Requires-Dist: pygetwindow>=0.0.9
Provides-Extra: dev
Requires-Dist: pytest>=8.0.0; extra == "dev"
Requires-Dist: pytest-cov>=4.1.0; extra == "dev"
Dynamic: author
Dynamic: license-file
Dynamic: requires-python
